{
    "argfile": {
        "name": "argfile",
        "remotes": {
            "origin": "git@github.com:epage/argfile.git",
            "upstream": "git@github.com:rust-cli/argfile.git"
        }
    },
    "argparse-benchmarks-rs": {
        "name": "argparse-benchmarks-rs",
        "remotes": {
            "origin": "git@github.com:epage/argparse-benchmarks-rs.git",
            "upstream": "git@github.com:rust-cli/argparse-benchmarks-rs.git"
        }
    },
    "assert_cmd": {
        "name": "assert_cmd",
        "remotes": {
            "origin": "git@github.com:epage/assert_cmd.git",
            "upstream": "git@github.com:assert-rs/assert_cmd.git"
        }
    },
    "assert_fs": {
        "name": "assert_fs",
        "remotes": {
            "origin": "git@github.com:epage/assert_fs.git",
            "upstream": "git@github.com:assert-rs/assert_fs.git"
        }
    },
    "book": {
        "name": "book",
        "remotes": {
            "origin": "git@github.com:epage/book.git",
            "upstream": "git@github.com:rust-cli/book.git"
        }
    },
    "cargo": {
        "name": "cargo",
        "remotes": {
            "origin": "git@github.com:epage/cargo.git",
            "upstream": "https://github.com/rust-lang/cargo.git"
        }
    },
    "cargo-api": {
        "name": "cargo-api",
        "remotes": {
            "origin": "git@github.com:epage/cargo-crate-api.git",
            "upstream": "git@github.com:crate-ci/cargo-crate-api.git"
        }
    },
    "cargo-breaking": {
        "name": "cargo-breaking",
        "remotes": {
            "origin": "git@github.com:epage/cargo-breaking.git",
            "upstream": "https://github.com/iomentum/cargo-breaking.git"
        }
    },
    "cargo-edit": {
        "name": "cargo-edit",
        "remotes": {
            "origin": "git@github.com:epage/cargo-edit.git",
            "upstream": "git@github.com:killercup/cargo-edit.git"
        }
    },
    "cargo-msrv": {
        "name": "cargo-msrv",
        "remotes": {
            "origin": "https://github.com/foresterre/cargo-msrv.git"
        }
    },
    "cargo-release": {
        "name": "cargo-release",
        "remotes": {
            "Person-93": "https://github.com/Person-93/cargo-release",
            "origin": "git@github.com:epage/cargo-release.git",
            "upstream": "git@github.com:crate-ci/cargo-release.git"
        }
    },
    "clap": {
        "name": "clap",
        "remotes": {
            "origin": "git@github.com:epage/clap.git",
            "upstream": "git@github.com:clap-rs/clap.git"
        }
    },
    "clap-cargo": {
        "name": "clap-cargo",
        "remotes": {
            "origin": "git@github.com:epage/clap-cargo.git",
            "upstream": "git@github.com:crate-ci/clap-cargo.git"
        }
    },
    "clap-verbosity-flag": {
        "name": "clap-verbosity-flag",
        "remotes": {
            "origin": "git@github.com:epage/clap-verbosity-flag.git",
            "upstream": "git@github.com:rust-cli/clap-verbosity-flag.git"
        }
    },
    "cli-wg": {
        "name": "cli-wg",
        "remotes": {
            "origin": "git@github.com:epage/cli-wg.git",
            "upstream": "git@github.com:rust-cli/team.git"
        }
    },
    "cobalt-org.github.io": {
        "name": "cobalt-org.github.io",
        "remotes": {
            "origin": "git@github.com:epage/cobalt-org.github.io.git",
            "upstream": "git@github.com:cobalt-org/cobalt-org.github.io.git"
        }
    },
    "cobalt.rs": {
        "name": "cobalt.rs",
        "remotes": {
            "origin": "git@github.com:epage/cobalt.rs.git",
            "upstream": "git@github.com:cobalt-org/cobalt.rs.git"
        }
    },
    "codegenrs": {
        "name": "codegenrs",
        "remotes": {
            "origin": "git@github.com:epage/codegenrs.git",
            "upstream": "git@github.com:crate-ci/codegenrs.git"
        }
    },
    "combine": {
        "name": "combine",
        "remotes": {
            "origin": "git@github.com:epage/combine.git",
            "upstream": "https://github.com/Marwes/combine.git"
        }
    },
    "committed": {
        "name": "committed",
        "remotes": {
            "origin": "git@github.com:epage/committed.git",
            "upstream": "git@github.com:crate-ci/committed.git"
        }
    },
    "concolor": {
        "name": "concolor",
        "remotes": {
            "origin": "git@github.com:epage/concolor.git",
            "upstream": "git@github.com:rust-cli/concolor.git"
        }
    },
    "epage.github.io": {
        "name": "epage.github.io",
        "remotes": {
            "origin": "git@github.com:epage/epage.github.io.git"
        }
    },
    "escargot": {
        "name": "escargot",
        "remotes": {
            "origin": "git@github.com:epage/escargot.git",
            "upstream": "git@github.com:crate-ci/escargot.git"
        }
    },
    "eztd": {
        "name": "eztd",
        "remotes": {
            "origin": "git@github.com:epage/eztd.git",
            "upstream": "git@github.com:epage/eztd.git"
        }
    },
    "gecko-dev": {
        "name": "gecko-dev",
        "remotes": {
            "origin": "https://github.com/mozilla/gecko-dev.git"
        }
    },
    "git-branch-stash": {
        "name": "git-branch-stash",
        "remotes": {
            "origin": "git@github.com:epage/git-branch-stash.git",
            "upstream": "git@github.com:gitext-rs/git-branch-stash.git"
        }
    },
    "git-branchless": {
        "name": "git-branchless",
        "remotes": {
            "origin": "git@github.com:epage/git-branchless.git",
            "upstream": "git@github.com:arxanas/git-branchless.git"
        }
    },
    "git-config-env": {
        "name": "git-config-env",
        "remotes": {
            "origin": "git@github.com:epage/git-config-env.git",
            "upstream": "git@github.com:gitext-rs/git-config-env.git"
        }
    },
    "git-conventional": {
        "name": "git-conventional",
        "remotes": {
            "origin": "git@github.com:epage/git-conventional.git",
            "upstream": "git@github.com:crate-ci/git-conventional.git"
        }
    },
    "git-fixture": {
        "name": "git-fixture",
        "remotes": {
            "origin": "git@github.com:epage/git-fixture.git",
            "upstream": "git@github.com:gitext-rs/git-fixture.git"
        }
    },
    "git-series": {
        "name": "git-series",
        "remotes": {
            "origin": "git@github.com:epage/git-series.git",
            "upstream": "https://github.com/git-series/git-series.git"
        }
    },
    "git-stack": {
        "name": "git-stack",
        "remotes": {
            "origin": "git@github.com:epage/git-stack.git",
            "upstream": "git@github.com:gitext-rs/git-stack.git"
        }
    },
    "git2-ext": {
        "name": "git2-ext",
        "remotes": {
            "origin": "git@github.com:epage/git2-ext.git",
            "upstream": "git@github.com:gitext-rs/git2-ext.git"
        }
    },
    "github-issues-import": {
        "name": "github-issues-import",
        "remotes": {
            "muff1nman": "https://github.com/muff1nman/github-issues-import",
            "origin": "https://github.com/IQAndreas/github-issues-import.git"
        }
    },
    "gtr": {
        "name": "gtr",
        "remotes": {
            "origin": "git@github.com:epage/gtr.git"
        }
    },
    "imperative": {
        "name": "imperative",
        "remotes": {
            "origin": "git@github.com:epage/imperative.git",
            "upstream": "git@github.com:crate-ci/imperative.git"
        }
    },
    "kstring": {
        "name": "kstring",
        "remotes": {
            "origin": "git@github.com:epage/kstring.git",
            "upstream": "git@github.com:cobalt-org/kstring.git"
        }
    },
    "linux": {
        "name": "linux",
        "remotes": {
            "origin": "https://github.com/westermo/linux.git"
        }
    },
    "liquid-rust": {
        "name": "liquid-rust",
        "remotes": {
            "origin": "git@github.com:epage/liquid-rust.git",
            "upstream": "git@github.com:cobalt-org/liquid-rust.git"
        }
    },
    "md-benchmarks-rs": {
        "name": "md-benchmarks-rs",
        "remotes": {
            "origin": "git@github.com:epage/md-benchmarks-rs.git",
            "upstream": "git@github.com:epage/md-benchmarks-rs.git"
        }
    },
    "mdBook": {
        "name": "mdBook",
        "remotes": {
            "origin": "git@github.com:epage/mdBook.git",
            "upstream": "https://github.com/rust-lang/mdBook.git"
        }
    },
    "nom": {
        "name": "nom",
        "remotes": {
            "origin": "git@github.com:epage/nom.git",
            "upstream": "https://github.com/Geal/nom.git"
        }
    },
    "predicates-rs": {
        "name": "predicates-rs",
        "remotes": {
            "origin": "git@github.com:epage/predicates-rs.git",
            "upstream": "git@github.com:assert-rs/predicates-rs.git"
        }
    },
    "proc-exit": {
        "name": "proc-exit",
        "remotes": {
            "origin": "git@github.com:epage/proc-exit.git",
            "upstream": "git@github.com:rust-cli/proc-exit.git"
        }
    },
    "pushgen": {
        "name": "pushgen",
        "remotes": {
            "origin": "git@github.com:epage/pushgen.git",
            "upstream": "git@github.com:AndWass/pushgen.git"
        }
    },
    "recaphub": {
        "name": "recaphub",
        "remotes": {
            "origin": "https://github.com/yaahc/recaphub.git"
        }
    },
    "ripgrep": {
        "name": "ripgrep",
        "remotes": {
            "origin": "git@github.com:epage/ripgrep.git",
            "upstream": "git@github.com:BurntSushi/ripgrep.git"
        }
    },
    "rls": {
        "name": "rls",
        "remotes": {
            "origin": "git@github.com:epage/rls.git",
            "upstream": "https://github.com/rust-lang/rls.git"
        }
    },
    "roff-rs": {
        "name": "roff-rs",
        "remotes": {
            "origin": "git@github.com:epage/roff-rs.git",
            "upstream": "git@github.com:rust-cli/roff-rs.git"
        }
    },
    "rust-rfcs": {
        "name": "rust-rfcs",
        "remotes": {
            "manishearth": "https://github.com/Manishearth/rfcs.git",
            "origin": "git@github.com:epage/rfcs.git",
            "upstream": "https://github.com/rust-lang/rfcs"
        }
    },
    "rust-semverver": {
        "name": "rust-semverver",
        "remotes": {
            "origin": "https://github.com/rust-lang/rust-semverver.git"
        }
    },
    "shadow-rs": {
        "name": "shadow-rs",
        "remotes": {
            "origin": "git@github.com:epage/shadow-rs.git",
            "upstream": "https://github.com/baoyachi/shadow-rs.git"
        }
    },
    "string-benchmarks-rs": {
        "name": "string-benchmarks-rs",
        "remotes": {
            "origin": "git@github.com:epage/string-benchmarks-rs.git",
            "upstream": "git@github.com:epage/string-benchmarks-rs.git"
        }
    },
    "taplo": {
        "name": "taplo",
        "remotes": {
            "origin": "git@github.com:epage/taplo.git",
            "upstream": "https://github.com/tamasfe/taplo.git"
        }
    },
    "termcolor": {
        "name": "termcolor",
        "remotes": {
            "origin": "git@github.com:epage/termcolor.git",
            "upstream": "https://github.com/BurntSushi/termcolor.git"
        }
    },
    "termtree": {
        "name": "termtree",
        "remotes": {
            "origin": "git@github.com:epage/termtree.git",
            "upstream": "git@github.com:rust-cli/termtree.git"
        }
    },
    "toml-rs": {
        "name": "toml-rs",
        "remotes": {
            "origin": "https://github.com/alexcrichton/toml-rs.git",
            "upstream": "https://github.com/alexcrichton/toml-rs.git"
        }
    },
    "toml-test": {
        "name": "toml-test",
        "remotes": {
            "origin": "git@github.com:epage/toml-test.git",
            "upstream": "https://github.com/BurntSushi/toml-test.git"
        }
    },
    "toml-test-rs": {
        "name": "toml-test-rs",
        "remotes": {
            "origin": "git@github.com:epage/toml-test-rs.git",
            "upstream": "git@github.com:epage/toml-test-rs.git"
        }
    },
    "toml_edit": {
        "name": "toml_edit",
        "remotes": {
            "origin": "git@github.com:epage/toml_edit.git",
            "upstream": "git@github.com:ordian/toml_edit.git"
        }
    },
    "treeline": {
        "name": "treeline",
        "remotes": {
            "origin": "git@github.com:epage/treeline.git",
            "upstream": "https://github.com/softprops/treeline.git"
        }
    },
    "trycmd": {
        "name": "trycmd",
        "remotes": {
            "origin": "git@github.com:epage/trycmd.git",
            "upstream": "git@github.com:assert-rs/trycmd.git"
        }
    },
    "typos": {
        "name": "typos",
        "remotes": {
            "origin": "git@github.com:epage/typos.git",
            "upstream": "git@github.com:crate-ci/typos.git"
        }
    },
    "unicode-xid": {
        "name": "unicode-xid",
        "remotes": {
            "origin": "git@github.com:epage/unicode-xid.git",
            "upstream": "git@github.com:unicode-rs/unicode-xid.git"
        }
    },
    "yansi": {
        "name": "yansi",
        "remotes": {
            "origin": "git@github.com:epage/yansi.git",
            "upstream": "git@github.com:SergioBenitez/yansi.git"
        }
    }
}
